runonce
setup.py
testfarmserver
testfarm/HttpFormPost.py
testfarm/__init__.py
testfarm/client.py
testfarm/client_test.py
testfarm/command.py
testfarm/command_test.py
testfarm/config.py
testfarm/config_test.py
testfarm/deansi.py
testfarm/deansi_test.py
testfarm/gitsandbox.py
testfarm/gitsandbox_test.py
testfarm/logger.py
testfarm/logger_test.py
testfarm/paramexpander.py
testfarm/paramexpander_test.py
testfarm/remotelogger.py
testfarm/remotelogger_test.py
testfarm/reporter.py
testfarm/reporter_test.py
testfarm/service.py
testfarm/service_test.py
testfarm/serviceproxy.py
testfarm/serviceproxy_test.py
testfarm/svnsandbox.py
testfarm/svnsandbox_test.py
testfarm/testfarmservice.py
testfarm/utils.py
testfarm/webgenerator.py
testfarm/webgenerator_test.py
testfarm.egg-info/PKG-INFO
testfarm.egg-info/SOURCES.txt
testfarm.egg-info/dependency_links.txt
testfarm.egg-info/requires.txt
testfarm.egg-info/top_level.txt
testfarm/v1/__init__.py
testfarm/v1/client.py
testfarm/v1/dirhelpers.py
testfarm/v1/ircreporter.py
testfarm/v1/listeners.py
testfarm/v1/loggerv2reporter.py
testfarm/v1/mailreporter.py
testfarm/v1/project.py
testfarm/v1/runner.py
testfarm/v1/task.py