Metadata-Version: 1.0
Name: testfarm
Version: 2.0
Summary: Testfarm, a continuous integration tool
Home-page: http://github.com/clam-project/testfarm/
Author: CLAM Project
Author-email: info@clam-project.org
License: GPL v3 or later
Platform: UNKNOWN
